FileHandler/__init__.py
FileHandler/core/__init__.py
FileHandler/core/engine.py
FileHandler/core/file_handler.py
FileHandler/core/item_handler.py
FileHandler/file_downloader/__init__.py
FileHandler/file_downloader/downloader.py
FileHandler/file_downloader/extractor.py
FileHandler/file_downloader/remover.py
FileHandler/file_reader/__init__.py
FileHandler/file_reader/item.py
FileHandler/file_reader/item_adapter.py
FileHandler/file_reader/item_loader.py
FileHandler/item_processor/__init__.py
FileHandler/item_processor/input.py
FileHandler/item_processor/output.py
FileHandler-1.0.14.dist-info/METADATA
FileHandler-1.0.14.dist-info/WHEEL
FileHandler-1.0.14.dist-info/top_level.txt
FileHandler-1.0.14.dist-info/RECORD
